[
{"title": "\u8bfa\u8d1d\u5c14\u5956\u54ea\u5bb6\u5f3a\uff1f", "link": "https://www.huxiu.com/article/320859.html", "posttime": "2019-10-09 17:02"},
{"title": "A\u80a1\u6216\u5c06\u8bde\u751f\u201c\u540c\u80a1\u4e0d\u540c\u6743\u7b2c\u4e00\u80a1\u201d\uff1f", "link": "https://www.huxiu.com/article/320808.html", "posttime": "2019-10-09 12:10"},
{"title": "\u201c\u65ad\u4f9b\u201d\u59d4\u5185\u745e\u62c9\uff0cAdobe\u6210\u4e86\u7f8e\u56fd\u5236\u88c1\u7684\u5de5\u5177\uff1f", "link": "https://www.huxiu.com/article/320822.html", "posttime": "2019-10-09 14:03"},
{"title": "\u7ecf\u5178\u5b9e\u9a8c\u518d\u906d\u8d28\u7591\uff0c\u81ea\u7531\u610f\u5fd7\u662f\u5426\u5b58\u5728\uff1f", "link": "https://www.huxiu.com/article/320845.html", "posttime": "2019-10-09 15:17"},
{"title": "\u5230\u300a\u5e7d\u7075\u884c\u52a8\uff1a\u65ad\u70b9\u300b\uff0c\u6b27\u7f8e\u5927\u5382\u4eec\u7ec8\u4e8e\u628a\u201c\u5f00\u653e\u4e16\u754c\u201d\u73a9\u6b7b\u4e86", "link": "https://www.huxiu.com/article/320773.html", "posttime": "2019-10-09 13:00"},
{"title": "\u6821\u56ed\u88c5\u4fee\u73af\u8bc4\u8d28\u91cf\u672a\u8fc7\u5173\uff0c\u600e\u53ef\u4ed3\u4fc3\u5165\u5b66\uff1f", "link": "https://www.huxiu.com/article/320839.html", "posttime": "2019-10-09 14:55"},
{"title": "\u4ece\u56fd\u4f01\u79bb\u804c\uff0c\u51e0\u4e2a\u4eba\u5728\u4e1c\u5317\u7684\u7535\u5668\u57ce\u91cc\u5f00\u4e86\u5bb6\u4e66\u5e97", "link": "https://www.huxiu.com/article/320801.html", "posttime": "2019-10-09 15:00"},
{"title": "\u6d17\u53bb\u6cb9\u5f69\u7684\u5c0f\u4e11\uff0c\u9732\u51fa\u4e86\u4f60\u6211\u7684\u8138", "link": "https://www.huxiu.com/article/320771.html", "posttime": "2019-10-09 11:00"},
{"title": "\u4e3a\u4ec0\u4e48\u201c\u5c0f\u4e11\u201d\u7684\u6765\u5386\u5982\u6b64\u795e\u79d8\uff1f", "link": "https://www.huxiu.com/article/320816.html?f=index_video", "posttime": "2019-10-09 14:02"},
{"title": "\u82b16000\u4e07\u201c\u6280\u672f\u64a4\u6362\u201d\u8303\u51b0\u51b0\u3001\u9ad8\u4e91\u7fd4\uff0c\u300a\u5df4\u6e05\u4f20\u300b\u5230\u5e95\u80fd\u64ad\u5417\uff1f", "link": "https://www.huxiu.com/article/320790.html", "posttime": "2019-10-09 16:16"},
{"title": "Arm\u6740\u5165\u81ea\u5b9a\u4e49\u6307\u4ee4\u96c6\uff0c\u6210\u7acb\u81ea\u52a8\u9a7e\u9a76\u8ba1\u7b97\u8054\u76df", "link": "https://www.huxiu.com/article/320810.html", "posttime": "2019-10-09 15:32"},
{"title": "\u4e0a\u6d77\u68a6\u9192\u4e92\u8054\u7f51", "link": "https://www.huxiu.com/article/320793.html", "posttime": "2019-10-09 16:37"},
{"title": "\u751f\u9c9c\u96f6\u552e\u4e0b\u534a\u573a\uff0c\u6218\u706b\u8fdc\u6bd4\u4e0a\u534a\u573a\u6fc0\u70c8", "link": "https://www.huxiu.com/article/320785.html", "posttime": "2019-10-09 15:50"},
{"title": "NBA \u642c\u8d77\u653f\u6cbb\u7838\u4e86\u81ea\u5df1\u7684\u811a", "link": "https://www.huxiu.com/article/320766.html", "posttime": "2019-10-09 08:04"},
{"title": "\u65e9\u719f\u7684\u8da3\u5934\u6761\u4f1a\u65e9\u8870\u5417\uff1f", "link": "https://www.huxiu.com/article/320761.html", "posttime": "2019-10-09 16:52"},
{"title": "\u3010\u864e\u55c5\u65e9\u62a5\u3011NBA\u4e2d\u56fd\u906d\u5408\u4f5c\u54c1\u724c\u629b\u5f03\uff1b\u4eba\u6c11\u65e5\u62a5\u6307\u8d23\u82f9\u679c\u4e3a\u66b4\u5f92\u201c\u62a4\u822a\u201d", "link": "https://www.huxiu.com/article/320765.html", "posttime": "2019-10-09 07:46"},
{"title": "\u201c\u732e\u793c\u65b9\u6cd5\u8bba\u201d", "link": "https://www.huxiu.com/article/320767.html", "posttime": "2019-10-09 08:06"},
{"title": "\u8c01\u5728\u6536\u5272\u5370\u5ea6\u7684\u793e\u4ea4\u5a92\u4f53", "link": "https://www.huxiu.com/article/320747.html", "posttime": "2019-10-09 10:52"},
{"title": "\u957f\u79df\u516c\u5bd3IPO\u751f\u6b7b\u65f6\u901f", "link": "https://www.huxiu.com/article/320792.html", "posttime": "2019-10-09 10:40"}
]